odoo/addons/stock_picking_product_availability_search/README.rst
odoo/addons/stock_picking_product_availability_search/__init__.py
odoo/addons/stock_picking_product_availability_search/__manifest__.py
odoo/addons/stock_picking_product_availability_search/i18n/it.po
odoo/addons/stock_picking_product_availability_search/i18n/stock_picking_product_availability_search.pot
odoo/addons/stock_picking_product_availability_search/models/__init__.py
odoo/addons/stock_picking_product_availability_search/models/stock_picking.py
odoo/addons/stock_picking_product_availability_search/readme/CONTRIBUTORS.rst
odoo/addons/stock_picking_product_availability_search/readme/DESCRIPTION.rst
odoo/addons/stock_picking_product_availability_search/static/description/icon.png
odoo/addons/stock_picking_product_availability_search/static/description/index.html
odoo/addons/stock_picking_product_availability_search/tests/__init__.py
odoo/addons/stock_picking_product_availability_search/tests/test_search.py
odoo/addons/stock_picking_product_availability_search/views/stock_picking.xml
odoo_addon_stock_picking_product_availability_search-15.0.1.0.1.3.dist-info/METADATA
odoo_addon_stock_picking_product_availability_search-15.0.1.0.1.3.dist-info/WHEEL
odoo_addon_stock_picking_product_availability_search-15.0.1.0.1.3.dist-info/top_level.txt
odoo_addon_stock_picking_product_availability_search-15.0.1.0.1.3.dist-info/RECORD
